octarine/__init__.py
octarine/__version__.py
octarine/config.py
octarine/controls.py
octarine/conversion.py
octarine/jupyter.py
octarine/plugins.py
octarine/selection.py
octarine/utils.py
octarine/viewer.py
octarine/visuals.py
octarine3d-0.3.2.dist-info/licenses/LICENSE
octarine3d-0.3.2.dist-info/METADATA
octarine3d-0.3.2.dist-info/WHEEL
octarine3d-0.3.2.dist-info/top_level.txt
octarine3d-0.3.2.dist-info/RECORD
