Metadata-Version: 2.4
Name: octarine3d
Version: 0.3.2
Summary: WGPU-based 3d viewer
Home-page: https://github.com/schlegelp/octarine
Author: Philipp Schlegel
Author-email: pms70@cam.ac.uk
License: BSD-2-Clause
Project-URL: Documentation, https://schlegelp.github.io/octarine/
Project-URL: Source, https://github.com/schlegelp/octarine
Project-URL: Changelog, https://github.com/schlegelp/octarine/releases
Keywords: 3D viewer WGPU pygfx
Classifier: Development Status :: 3 - Alpha
Classifier: Intended Audience :: Science/Research
Classifier: Topic :: Scientific/Engineering :: Bio-Informatics
Classifier: Programming Language :: Python :: 3
Classifier: Programming Language :: Python :: 3.9
Classifier: Programming Language :: Python :: 3.10
Classifier: Programming Language :: Python :: 3.11
Classifier: Programming Language :: Python :: 3.12
Classifier: Programming Language :: Python :: 3.13
Requires-Python: >=3.9
License-File: LICENSE
Requires-Dist: pygfx==0.14.0
Requires-Dist: numpy
Requires-Dist: pypng
Requires-Dist: six
Requires-Dist: cmap
Requires-Dist: trimesh[easy]
Requires-Dist: importlib-metadata>=4.6
Provides-Extra: all
Requires-Dist: jupyter_rfb; extra == "all"
Requires-Dist: PySide6-Essentials; extra == "all"
Requires-Dist: ipywidgets; extra == "all"
Requires-Dist: sidecar; extra == "all"
Provides-Extra: docs
Requires-Dist: mkdocs; extra == "docs"
Requires-Dist: mkdocs-material[imaging]; extra == "docs"
Requires-Dist: mkdocstrings-python; extra == "docs"
Requires-Dist: mkdocs-minify-plugin; extra == "docs"
Requires-Dist: mkdocs-literate-nav; extra == "docs"
Requires-Dist: mkdocs-gen-files; extra == "docs"
Requires-Dist: mkdocs-glightbox; extra == "docs"
Requires-Dist: mkdocs-section-index; extra == "docs"
Provides-Extra: dev
Requires-Dist: pytest; extra == "dev"
Dynamic: author
Dynamic: author-email
Dynamic: classifier
Dynamic: description
Dynamic: description-content-type
Dynamic: home-page
Dynamic: keywords
Dynamic: license
Dynamic: license-file
Dynamic: project-url
Dynamic: provides-extra
Dynamic: requires-dist
Dynamic: requires-python
Dynamic: summary
